graph_context/__init__.py
graph_context/_version.py
graph_context/context_base.py
graph_context/event_system.py
graph_context/exceptions.py
graph_context/interface.py
graph_context/store.py
graph_context/traversal.py
graph_context/caching/__init__.py
graph_context/caching/cache_manager.py
graph_context/caching/cache_store.py
graph_context/caching/cache_store_manager.py
graph_context/caching/cached_context.py
graph_context/caching/config.py
graph_context/interfaces/__init__.py
graph_context/interfaces/store.py
graph_context/manager/__init__.py
graph_context/manager/entity_manager.py
graph_context/manager/query_manager.py
graph_context/manager/relation_manager.py
graph_context/manager/transaction_manager.py
graph_context/stores/memory_store.py
graph_context/types/__init__.py
graph_context/types/type_base.py
graph_context/types/validators.py
graph_context/validation/__init__.py
graph_context/validation/schema_validator.py
graph_context-0.3.6.dist-info/METADATA
graph_context-0.3.6.dist-info/WHEEL
graph_context-0.3.6.dist-info/licenses/LICENSE
graph_context-0.3.6.dist-info/RECORD
