Metadata-Version: 2.4
Name: graph-context
Version: 0.3.6
Summary: Graph Context component for Knowledge Graph Assisted Research IDE
Project-URL: Homepage, https://github.com/beanone/graph-context
Project-URL: Repository, https://github.com/beanone/graph-context
Author-email: Beanone Team <beanone@example.com>
License-Expression: MIT
License-File: LICENSE
Keywords: context,graph,ide,knowledge graph,research
Classifier: Development Status :: 3 - Alpha
Classifier: Intended Audience :: Developers
Classifier: License :: OSI Approved :: MIT License
Classifier: Programming Language :: Python :: 3.12
Classifier: Topic :: Scientific/Engineering :: Artificial Intelligence
Classifier: Topic :: Software Development :: Libraries :: Python Modules
Requires-Python: >=3.10
Requires-Dist: asyncio>=3.4.3
Requires-Dist: cachetools>=5.3.2
Requires-Dist: pydantic>=2.5.2
Requires-Dist: typing-extensions>=4.8.0
Provides-Extra: dev
Requires-Dist: hypothesis>=6.87.1; extra == 'dev'
Requires-Dist: pre-commit>=3.5.0; extra == 'dev'
Requires-Dist: pytest-asyncio>=0.21.1; extra == 'dev'
Requires-Dist: pytest-cov>=4.1.0; extra == 'dev'
Requires-Dist: pytest>=7.4.3; extra == 'dev'
Requires-Dist: ruff>=0.1.6; extra == 'dev'
